README.md
setup.py
erclient/__init__.py
erclient/address.py
erclient/adsource.py
erclient/attachment.py
erclient/base.py
erclient/candidate.py
erclient/communication.py
erclient/company.py
erclient/config.py
erclient/contact.py
erclient/customfield.py
erclient/department.py
erclient/estaff.py
erclient/foldergroup.py
erclient/list.py
erclient/owner.py
erclient/position.py
erclient/recruiter.py
erclient/seed.py
erclient/tests.py
erclient/user.py
erclient.egg-info/PKG-INFO
erclient.egg-info/SOURCES.txt
erclient.egg-info/dependency_links.txt
erclient.egg-info/not-zip-safe
erclient.egg-info/requires.txt
erclient.egg-info/top_level.txt