Metadata-Version: 1.0
Name: erclient
Version: 0.95
Summary: Client for Erecruit API 2.0 with Fallback to 1.0
Home-page: https://github.com/pdbethke/erclient
Author: siteshell.net
Author-email: pdbethke@siteshell.net
License: LICENSE.txt
Platform: OS Independent
